setup.cfg
setup.py
tests/__init__.py
tests/test.py
tests/test_helpers.py
tests/test_layers.py
tests/test_metrics.py
tests/test_models.py
tests/test_models_loading_scope.py
tests/test_objectives.py
tests/test_validation_monitors.py
tflearn/__init__.py
tflearn/activations.py
tflearn/callbacks.py
tflearn/collections.py
tflearn/config.py
tflearn/data_augmentation.py
tflearn/data_flow.py
tflearn/data_preprocessing.py
tflearn/data_utils.py
tflearn/initializations.py
tflearn/losses.py
tflearn/metrics.py
tflearn/objectives.py
tflearn/optimizers.py
tflearn/summaries.py
tflearn/utils.py
tflearn/variables.py
tflearn.egg-info/PKG-INFO
tflearn.egg-info/SOURCES.txt
tflearn.egg-info/dependency_links.txt
tflearn.egg-info/requires.txt
tflearn.egg-info/top_level.txt
tflearn/datasets/__init__.py
tflearn/datasets/cifar10.py
tflearn/datasets/cifar100.py
tflearn/datasets/imdb.py
tflearn/datasets/mnist.py
tflearn/datasets/oxflower17.py
tflearn/datasets/svhn.py
tflearn/datasets/titanic.py
tflearn/estimators/__init__.py
tflearn/estimators/cluster.py
tflearn/estimators/ensemble.py
tflearn/estimators/linear_model.py
tflearn/estimators/neural_network.py
tflearn/helpers/__init__.py
tflearn/helpers/evaluator.py
tflearn/helpers/generator.py
tflearn/helpers/regularizer.py
tflearn/helpers/summarizer.py
tflearn/helpers/trainer.py
tflearn/layers/__init__.py
tflearn/layers/conv.py
tflearn/layers/core.py
tflearn/layers/embedding_ops.py
tflearn/layers/estimator.py
tflearn/layers/merge_ops.py
tflearn/layers/normalization.py
tflearn/layers/recurrent.py
tflearn/models/__init__.py
tflearn/models/dnn.py
tflearn/models/generator.py
tflearn/templates/__init__.py
tflearn/templates/cnn.py