Metadata-Version: 1.1
Name: tflearn
Version: 0.3
Summary: Deep Learning Library featuring a higher-level API for Tensorflow
Home-page: https://github.com/tflearn/tflearn
Author: TFLearn contributors
Author-email: aymeric.damien@gmail.com
License: MIT
Download-URL: https://github.com/tflearn/tflearn/tarball/0.3
Keywords: TFLearn,TensorFlow,Deep Learning,Machine Learning,Neural Networks,AI
Platform: UNKNOWN
Classifier: Programming Language :: Python
Classifier: Operating System :: OS Independent
Classifier: Intended Audience :: Developers
Classifier: Intended Audience :: Science/Research
Classifier: Topic :: Scientific/Engineering :: Artificial Intelligence
